{
    "from": "מדויקים",
    "to": "גילמן",
    "data": [
        {
            "lat": "32.1131049",
            "lon": "34.8058278",
            "text": "נצא מבניין מדויקים, לפנינו 8 מדרגות. \nנרד אותם מצד שמאל ונחזיק במעקה. מיד בסיום המדרגות ישנו פח מבטון, נעבור אותו ונמשיך ללכת בקו ישר על השביל המחוספס עוד 2 מטר עד שנגיע לכר דשא שמשמאל לשביל."
        },
        {
            "lat": "32.1131105",
            "lon": "34.8057373",
            "text": "נמשיך ישר בשיל המחוספס כשהדשא לשמאלנו עוד 25 מטרים עד להגעה לסלעים בצד השביל שבולטים אל תוך השביל.\n"
        },
        {
            "lat": "32.1131151",
            "lon": "34.8055116",
            "text": "כאשר הגענו לסלעים הבולטים, נעבור אותם כשהם משמאלנו ונמשיך ישר עוד 10 מטרים עד למעבר צומת הולכי רגל המגיעים משמאל."
        },
        {
            "lat": "32.1131023",
            "lon": "34.805396",
            "text": "ניצמד לצד שמאל של השביל- לאורכו ישנם אבני שפה כמו מדרכה.\nנמשיך ללכת עוד 35 מטרים על השביל המחוספס עד לסיום אבני השפה משמאלנו."
        },
        {
            "lat": "32.1130528",
            "lon": "34.8050515",
            "text": "לאחר שאבני השפה מסתיימות, נמשיך ישר כ-2 מטרים עד שנרגיש שוב באבני שפה דומות. שוב נישאר לצידם כאשר הם לשמאלנו ונמשיך ישר עוד 30 מטר עד לסיומן."
        },
        {
            "lat": "32.1130636",
            "lon": "34.8047396",
            "text": "בסיום אבני השפה, נמשיך ישר בשביל המחוספס עוד 10  מטרים עד להגעה לבניין, ניזהר מעץ שלימיננו ומשיחים לשמאלנו."
        },
        {
            "lat": "32.1131046",
            "lon": "34.8046353",
            "text": "הגענו לבניין גילמן, נפנה 90 מעלות שמאלה ונכנס אל הבניין."
        }
    ]
}